cryptoverse/__init__.py
cryptoverse/__main__.py
cryptoverse/exceptions.py
cryptoverse/base/__init__.py
cryptoverse/base/interface/__init__.py
cryptoverse/base/interface/exchange_interface.py
cryptoverse/base/interface/explorer_interface.py
cryptoverse/base/rest/__init__.py
cryptoverse/base/rest/request.py
cryptoverse/base/rest/response.py
cryptoverse/base/rest/rest_client.py
cryptoverse/base/scrape/__init__.py
cryptoverse/base/scrape/scrape_client.py
cryptoverse/domain/__init__.py
cryptoverse/domain/accounts.py
cryptoverse/domain/amounts.py
cryptoverse/domain/balances.py
cryptoverse/domain/constants.py
cryptoverse/domain/credentials.py
cryptoverse/domain/exchanges.py
cryptoverse/domain/instruments.py
cryptoverse/domain/keystores.py
cryptoverse/domain/lends.py
cryptoverse/domain/markets.py
cryptoverse/domain/object_list.py
cryptoverse/domain/offers.py
cryptoverse/domain/orders.py
cryptoverse/domain/pairs.py
cryptoverse/domain/portfolio.py
cryptoverse/domain/positions.py
cryptoverse/domain/tickers.py
cryptoverse/domain/trades.py
cryptoverse/domain/wallets.py
cryptoverse/exchanges/__init__.py
cryptoverse/exchanges/interfaces/__init__.py
cryptoverse/exchanges/interfaces/bitfinex_interface.py
cryptoverse/exchanges/interfaces/bl3p_interface.py
cryptoverse/exchanges/interfaces/kraken_interface.py
cryptoverse/exchanges/interfaces/poloniex_interface.py
cryptoverse/exchanges/rest/__init__.py
cryptoverse/exchanges/rest/bitfinex_rest.py
cryptoverse/exchanges/rest/bl3p_rest.py
cryptoverse/exchanges/rest/kraken_rest.py
cryptoverse/exchanges/rest/poloniex_rest.py
cryptoverse/exchanges/scrape/__init__.py
cryptoverse/exchanges/scrape/bitfinex_scrape.py
cryptoverse/exchanges/socket/__init__.py
cryptoverse/explorers/__init__.py
cryptoverse/explorers/rest/__init__.py
cryptoverse/notifications/__init__.py
cryptoverse/providers/__init__.py
cryptoverse/providers/rest/__init__.py
cryptoverse/providers/scrape/__init__.py
cryptoverse-0.0.1.dev6.dist-info/METADATA
cryptoverse-0.0.1.dev6.dist-info/RECORD
cryptoverse-0.0.1.dev6.dist-info/WHEEL
cryptoverse-0.0.1.dev6.dist-info/entry_points.txt
cryptoverse-0.0.1.dev6.dist-info/top_level.txt
cryptoverse-0.0.1.dev6.dist-info/zip-safe
