Metadata-Version: 2.1
Name: cryptoverse
Version: 0.0.1.dev6
Summary: Cryptocurrency focused quantitative finance tools.
Home-page: https://github.com/quantimoto/cryptoverse
Maintainer: Bruteque
Maintainer-email: quantimoto@brutesque.com
License: GPLv3
Keywords: cryptocurrency,quantitative,finance
Platform: UNKNOWN
Classifier: Programming Language :: Python
Classifier: Programming Language :: Python :: 3
Classifier: Development Status :: 1 - Planning
Classifier: Environment :: Console
Classifier: Intended Audience :: Developers
Classifier: License :: OSI Approved :: GNU General Public License v3 (GPLv3)
Classifier: Natural Language :: English
Classifier: Operating System :: OS Independent
Classifier: Topic :: Software Development :: Libraries :: Python Modules
Classifier: Topic :: Office/Business :: Financial
Requires-Dist: beautifulsoup4 (==4.6.1)
Requires-Dist: dict-recursive-update (==1.0.1)
Requires-Dist: libkeepass (==0.2.0)
Requires-Dist: matplotlib (==2.2.2)
Requires-Dist: memoized-property (==1.0.3)
Requires-Dist: mpl-finance (==0.10.0)
Requires-Dist: pandas (==0.23.4)
Requires-Dist: pytest (==3.4.1)
Requires-Dist: pytest-runner (==4.0)
Requires-Dist: requests (==2.20.0)
Requires-Dist: retry (==0.9.2)
Requires-Dist: termcolor (==1.1.0)
Requires-Dist: twine (==1.9.1)
